README.rst
setup.py
cfdns/__init__.py
cfdns.egg-info/PKG-INFO
cfdns.egg-info/SOURCES.txt
cfdns.egg-info/dependency_links.txt
cfdns.egg-info/entry_points.txt
cfdns.egg-info/requires.txt
cfdns.egg-info/top_level.txt