Metadata-Version: 1.1
Name: cfdns
Version: 0.1.1
Summary: Command line tool for manipulating DNS of CloudFlare hosted domains
Home-page: https://github.com/madflojo/cfdns
Author: madflojo
Author-email: ben@bencane.com
License: Apache 2
Platform: UNKNOWN
Classifier: License :: OSI Approved :: Apache Software License
Classifier: Topic :: Internet :: Name Service (DNS)
